LICENSE.txt
MANIFEST.in
README.rst
requirements.txt
setup.py
blueflask/__init__.py
blueflask/cli.py
blueflask.egg-info/PKG-INFO
blueflask.egg-info/SOURCES.txt
blueflask.egg-info/dependency_links.txt
blueflask.egg-info/entry_points.txt
blueflask.egg-info/not-zip-safe
blueflask.egg-info/requires.txt
blueflask.egg-info/top_level.txt
blueflask/templates/app_template/config.py
blueflask/templates/app_template/run.py
blueflask/templates/app_template/app/__init__.py
blueflask/templates/app_template/app/app.py
blueflask/templates/app_template/app/blueprints/__init__.py
blueflask/templates/app_template/app/blueprints/demo/__init__.py
blueflask/templates/app_template/app/blueprints/demo/config.py
blueflask/templates/app_template/app/blueprints/demo/urls.py
blueflask/templates/app_template/app/blueprints/demo/views.py
blueflask/templates/app_template/app/blueprints/main/__init__.py
blueflask/templates/app_template/app/blueprints/main/config.py
blueflask/templates/app_template/app/blueprints/main/urls.py
blueflask/templates/app_template/app/blueprints/main/views.py