Metadata-Version: 1.1
Name: blueflask
Version: 0.1.4
Summary: Flask boilerplate to create an application with the idea of pluggable blueprints.
Home-page: https://github.com/harph/blueflask
Author: Harrington Joseph
Author-email: hello@hjoseph.com
License: MIT license
Keywords: blueflask
Platform: UNKNOWN
Classifier: Development Status :: 2 - Pre-Alpha
Classifier: Intended Audience :: Developers
Classifier: License :: OSI Approved :: MIT License
Classifier: Natural Language :: English
Classifier: Programming Language :: Python :: 2.7
Classifier: Programming Language :: Python :: 3
Classifier: Programming Language :: Python :: 3.3
Classifier: Programming Language :: Python :: 3.4
Classifier: Programming Language :: Python :: 3.5
